[
  {
    "id": 1,
    "title": "化学课程系统安排",
    "series": "化学",
    "date": "2026-06-29",
    "path": "化学/化学课程系统安排.md"
  },
  {
    "id": 2,
    "title": "0 物质的量——微观和宏观数量关系的桥梁",
    "series": "化学",
    "date": "2026-06-29",
    "path": "化学/理论课讲义/0 物质的量——微观和宏观数量关系的桥梁.md"
  },
  {
    "id": 3,
    "title": "1 英语语法核心理论概览",
    "series": "英语",
    "date": "2026-06-29",
    "path": "英语/语法课讲义/1 英语语法核心理论概览.md"
  },
  {
    "id": 4,
    "title": "2 核心词理论",
    "series": "英语",
    "date": "2026-06-29",
    "path": "英语/语法课讲义/2 核心词理论.md"
  },
  {
    "id": 5,
    "title": "精读任务-7",
    "series": "英语",
    "date": "2026-06-29",
    "path": "英语/课后练习/精读任务-7.md"
  }
]